delay_proxy-0.1.2.data/scripts/run-delay-proxy
delay_proxy-0.1.2.dist-info/METADATA
delay_proxy-0.1.2.dist-info/RECORD
delay_proxy-0.1.2.dist-info/WHEEL
delay_proxy-0.1.2.dist-info/top_level.txt
delayproxy/__init__.py
delayproxy/basicproxy.py
