Metadata-Version: 2.1
Name: delay-proxy
Version: 0.1.2
Summary: An HTTP proxy that introduces network delays to the response from the server
Home-page: https://github.com/maribelacosta/delay-proxy
Author: Maribel Acosta
Author-email: maribel.acosta@kit.edu
License: Apache 2
Platform: UNKNOWN
Classifier: License :: OSI Approved :: Apache Software License
Classifier: Topic :: System :: Networking
